[{"neighbourhood_group": "Bronx", "count": 207, "m_price": 33.73913043478261, "m_review": 22.17391304347826}, {"neighbourhood_group": "Bronx", "count": 14, "m_price": 103.92857142857143, "m_review": 35.214285714285715}, {"neighbourhood_group": "Bronx", "count": 49, "m_price": 114.53061224489795, "m_review": 28.46938775510204}, {"neighbourhood_group": "Bronx", "count": 30, "m_price": 126.06666666666666, "m_review": 28.333333333333332}, {"neighbourhood_group": "Bronx", "count": 32, "m_price": 142.15625, "m_review": 24.0}, {"neighbourhood_group": "Bronx", "count": 25, "m_price": 150.6, "m_review": 18.08}, {"neighbourhood_group": "Bronx", "count": 14, "m_price": 167.42857142857142, "m_review": 11.714285714285714}, {"neighbourhood_group": "Bronx", "count": 17, "m_price": 195.8235294117647, "m_review": 16.470588235294116}, {"neighbourhood_group": "Bronx", "count": 3, "m_price": 222.66666666666666, "m_review": 0.0}, {"neighbourhood_group": "Bronx", "count": 8, "m_price": 247.125, "m_review": 30.0}, {"neighbourhood_group": "Bronx", "count": 16, "m_price": 309.1875, "m_review": 7.9375}, {"neighbourhood_group": "Bronx", "count": 107, "m_price": 45.11214953271028, "m_review": 31.19626168224299}, {"neighbourhood_group": "Bronx", "count": 18, "m_price": 646.0, "m_review": 10.11111111111111}, {"neighbourhood_group": "Bronx", "count": 104, "m_price": 51.88461538461539, "m_review": 34.13461538461539}, {"neighbourhood_group": "Bronx", "count": 81, "m_price": 59.44444444444444, "m_review": 29.123456790123456}, {"neighbourhood_group": "Bronx", "count": 75, "m_price": 65.56, "m_review": 23.72}, {"neighbourhood_group": "Bronx", "count": 87, "m_price": 73.22988505747126, "m_review": 19.402298850574713}, {"neighbourhood_group": "Bronx", "count": 70, "m_price": 79.4, "m_review": 23.242857142857144}, {"neighbourhood_group": "Bronx", "count": 57, "m_price": 86.82456140350877, "m_review": 36.31578947368421}, {"neighbourhood_group": "Bronx", "count": 77, "m_price": 98.51948051948052, "m_review": 31.415584415584416}, {"neighbourhood_group": "Brooklyn", "count": 1495, "m_price": 34.69765886287625, "m_review": 15.40133779264214}, {"neighbourhood_group": "Brooklyn", "count": 223, "m_price": 104.17040358744394, "m_review": 34.11210762331839}, {"neighbourhood_group": "Brooklyn", "count": 1285, "m_price": 115.52295719844358, "m_review": 28.58443579766537}, {"neighbourhood_group": "Brooklyn", "count": 910, "m_price": 126.71758241758242, "m_review": 29.51098901098901}, {"neighbourhood_group": "Brooklyn", "count": 833, "m_price": 140.91356542617046, "m_review": 37.86434573829532}, {"neighbourhood_group": "Brooklyn", "count": 920, "m_price": 150.4891304347826, "m_review": 23.028260869565216}, {"neighbourhood_group": "Brooklyn", "count": 904, "m_price": 167.25553097345133, "m_review": 32.991150442477874}, {"neighbourhood_group": "Brooklyn", "count": 1203, "m_price": 192.93100581878636, "m_review": 25.044056525353284}, {"neighbourhood_group": "Brooklyn", "count": 360, "m_price": 218.7277777777778, "m_review": 29.45}, {"neighbourhood_group": "Brooklyn", "count": 545, "m_price": 248.1302752293578, "m_review": 22.209174311926606}, {"neighbourhood_group": "Brooklyn", "count": 607, "m_price": 307.9802306425041, "m_review": 22.28500823723229}, {"neighbourhood_group": "Brooklyn", "count": 1254, "m_price": 45.42982456140351, "m_review": 17.87878787878788}, {"neighbourhood_group": "Brooklyn", "count": 543, "m_price": 732.0128913443831, "m_review": 15.11049723756906}, {"neighbourhood_group": "Brooklyn", "count": 1565, "m_price": 51.979552715654954, "m_review": 18.21150159744409}, {"neighbourhood_group": "Brooklyn", "count": 1098, "m_price": 59.40163934426229, "m_review": 22.97632058287796}, {"neighbourhood_group": "Brooklyn", "count": 1160, "m_price": 65.44137931034483, "m_review": 24.631034482758622}, {"neighbourhood_group": "Brooklyn", "count": 1435, "m_price": 72.61881533101045, "m_review": 21.51567944250871}, {"neighbourhood_group": "Brooklyn", "count": 857, "m_price": 79.48541423570595, "m_review": 24.312718786464412}, {"neighbourhood_group": "Brooklyn", "count": 1218, "m_price": 87.46551724137932, "m_review": 27.939244663382595}, {"neighbourhood_group": "Brooklyn", "count": 1689, "m_price": 98.22320899940793, "m_review": 26.510953226761398}, {"neighbourhood_group": "Manhattan", "count": 382, "m_price": 34.77748691099477, "m_review": 12.654450261780104}, {"neighbourhood_group": "Manhattan", "count": 243, "m_price": 104.2880658436214, "m_review": 31.48559670781893}, {"neighbourhood_group": "Manhattan", "count": 1420, "m_price": 115.21760563380282, "m_review": 24.506338028169015}, {"neighbourhood_group": "Manhattan", "count": 1016, "m_price": 126.87303149606299, "m_review": 24.169291338582678}, {"neighbourhood_group": "Manhattan", "count": 1160, "m_price": 140.62586206896552, "m_review": 24.725}, {"neighbourhood_group": "Manhattan", "count": 1216, "m_price": 150.54194078947367, "m_review": 17.69983552631579}, {"neighbourhood_group": "Manhattan", "count": 1410, "m_price": 167.7177304964539, "m_review": 20.415602836879433}, {"neighbourhood_group": "Manhattan", "count": 2338, "m_price": 192.6184773310522, "m_review": 20.82720273738238}, {"neighbourhood_group": "Manhattan", "count": 885, "m_price": 217.74689265536722, "m_review": 19.48361581920904}, {"neighbourhood_group": "Manhattan", "count": 1557, "m_price": 246.76107899807323, "m_review": 14.750802825947334}, {"neighbourhood_group": "Manhattan", "count": 1703, "m_price": 308.00939518496773, "m_review": 15.510863182618907}, {"neighbourhood_group": "Manhattan", "count": 340, "m_price": 45.75588235294118, "m_review": 24.102941176470587}, {"neighbourhood_group": "Manhattan", "count": 1792, "m_price": 720.4787946428571, "m_review": 12.246651785714286}, {"neighbourhood_group": "Manhattan", "count": 621, "m_price": 51.99677938808374, "m_review": 18.615136876006442}, {"neighbourhood_group": "Manhattan", "count": 488, "m_price": 59.44877049180328, "m_review": 22.5327868852459}, {"neighbourhood_group": "Manhattan", "count": 683, "m_price": 65.79209370424597, "m_review": 26.81259150805271}, {"neighbourhood_group": "Manhattan", "count": 872, "m_price": 72.7591743119266, "m_review": 24.985091743119266}, {"neighbourhood_group": "Manhattan", "count": 698, "m_price": 79.44985673352436, "m_review": 26.00429799426934}, {"neighbourhood_group": "Manhattan", "count": 1092, "m_price": 87.50274725274726, "m_review": 28.923076923076923}, {"neighbourhood_group": "Manhattan", "count": 1745, "m_price": 98.32607449856734, "m_review": 26.296848137535818}, {"neighbourhood_group": "Queens", "count": 665, "m_price": 34.747368421052634, "m_review": 22.33984962406015}, {"neighbourhood_group": "Queens", "count": 58, "m_price": 104.10344827586206, "m_review": 30.586206896551722}, {"neighbourhood_group": "Queens", "count": 307, "m_price": 115.07817589576547, "m_review": 26.84039087947883}, {"neighbourhood_group": "Queens", "count": 183, "m_price": 126.53551912568307, "m_review": 27.939890710382514}, {"neighbourhood_group": "Queens", "count": 174, "m_price": 140.30459770114942, "m_review": 21.362068965517242}, {"neighbourhood_group": "Queens", "count": 172, "m_price": 150.3953488372093, "m_review": 21.267441860465116}, {"neighbourhood_group": "Queens", "count": 131, "m_price": 167.54961832061068, "m_review": 19.015267175572518}, {"neighbourhood_group": "Queens", "count": 218, "m_price": 192.8302752293578, "m_review": 21.98165137614679}, {"neighbourhood_group": "Queens", "count": 43, "m_price": 219.93023255813952, "m_review": 14.953488372093023}, {"neighbourhood_group": "Queens", "count": 98, "m_price": 248.70408163265307, "m_review": 16.387755102040817}, {"neighbourhood_group": "Queens", "count": 101, "m_price": 303.44554455445547, "m_review": 23.623762376237625}, {"neighbourhood_group": "Queens", "count": 492, "m_price": 45.6260162601626, "m_review": 34.733739837398375}, {"neighbourhood_group": "Queens", "count": 80, "m_price": 778.8625, "m_review": 10.975}, {"neighbourhood_group": "Queens", "count": 613, "m_price": 52.1141924959217, "m_review": 33.44535073409462}, {"neighbourhood_group": "Queens", "count": 415, "m_price": 59.40481927710843, "m_review": 31.46265060240964}, {"neighbourhood_group": "Queens", "count": 364, "m_price": 65.5989010989011, "m_review": 35.32692307692308}, {"neighbourhood_group": "Queens", "count": 445, "m_price": 72.52359550561798, "m_review": 26.24943820224719}, {"neighbourhood_group": "Queens", "count": 262, "m_price": 79.40458015267176, "m_review": 32.774809160305345}, {"neighbourhood_group": "Queens", "count": 361, "m_price": 87.41828254847645, "m_review": 25.994459833795013}, {"neighbourhood_group": "Queens", "count": 484, "m_price": 98.39462809917356, "m_review": 28.175619834710744}, {"neighbourhood_group": "Staten Island", "count": 64, "m_price": 33.765625, "m_review": 36.21875}, {"neighbourhood_group": "Staten Island", "count": 6, "m_price": 104.83333333333333, "m_review": 40.666666666666664}, {"neighbourhood_group": "Staten Island", "count": 20, "m_price": 114.95, "m_review": 28.7}, {"neighbourhood_group": "Staten Island", "count": 10, "m_price": 126.6, "m_review": 37.6}, {"neighbourhood_group": "Staten Island", "count": 9, "m_price": 138.44444444444446, "m_review": 29.22222222222222}, {"neighbourhood_group": "Staten Island", "count": 11, "m_price": 150.45454545454547, "m_review": 13.181818181818182}, {"neighbourhood_group": "Staten Island", "count": 5, "m_price": 168.2, "m_review": 41.0}, {"neighbourhood_group": "Staten Island", "count": 17, "m_price": 192.52941176470588, "m_review": 33.11764705882353}, {"neighbourhood_group": "Staten Island", "count": 1, "m_price": 221.0, "m_review": 0.0}, {"neighbourhood_group": "Staten Island", "count": 6, "m_price": 246.33333333333334, "m_review": 12.833333333333334}, {"neighbourhood_group": "Staten Island", "count": 10, "m_price": 291.1, "m_review": 17.5}, {"neighbourhood_group": "Staten Island", "count": 21, "m_price": 46.714285714285715, "m_review": 31.142857142857142}, {"neighbourhood_group": "Staten Island", "count": 8, "m_price": 1281.75, "m_review": 0.625}, {"neighbourhood_group": "Staten Island", "count": 38, "m_price": 52.10526315789474, "m_review": 23.81578947368421}, {"neighbourhood_group": "Staten Island", "count": 13, "m_price": 58.76923076923077, "m_review": 59.69230769230769}, {"neighbourhood_group": "Staten Island", "count": 26, "m_price": 65.53846153846153, "m_review": 26.115384615384617}, {"neighbourhood_group": "Staten Island", "count": 37, "m_price": 73.08108108108108, "m_review": 50.08108108108108}, {"neighbourhood_group": "Staten Island", "count": 15, "m_price": 79.26666666666667, "m_review": 29.533333333333335}, {"neighbourhood_group": "Staten Island", "count": 21, "m_price": 86.33333333333333, "m_review": 21.38095238095238}, {"neighbourhood_group": "Staten Island", "count": 35, "m_price": 98.74285714285715, "m_review": 23.914285714285715}]